{
  "$schema": "http://json.schemastore.org/sarif-1.0.0",
  "version": "1.0.0",
  "runs": [
    {
      "tool": {
        "name": "Compilador do Microsoft (R) Visual C#",
        "version": "3.4.0.0",
        "fileVersion": "3.4.1-beta4-19614-01 (16504609)",
        "semanticVersion": "3.4.0",
        "language": "pt-BR"
      },
      "results": [
        {
          "ruleId": "S125",
          "level": "warning",
          "message": "Remove this commented out code.",
          "locations": [
            {
              "resultFile": {
                "uri": "file:///C:/Users/Mauricio/source/repos/martloc/martloc.infrastructure/Data/BackendContext.cs",
                "region": {
                  "startLine": 18,
                  "startColumn": 9,
                  "endLine": 18,
                  "endColumn": 54
                }
              }
            }
          ],
          "properties": {
            "warningLevel": 1
          }
        },
        {
          "ruleId": "S125",
          "level": "warning",
          "message": "Remove this commented out code.",
          "locations": [
            {
              "resultFile": {
                "uri": "file:///C:/Users/Mauricio/source/repos/martloc/martloc.infrastructure/Data/BackendContext.cs",
                "region": {
                  "startLine": 35,
                  "startColumn": 13,
                  "endLine": 35,
                  "endColumn": 65
                }
              }
            }
          ],
          "properties": {
            "warningLevel": 1
          }
        },
        {
          "ruleId": "S125",
          "level": "warning",
          "message": "Remove this commented out code.",
          "locations": [
            {
              "resultFile": {
                "uri": "file:///C:/Users/Mauricio/source/repos/martloc/martloc.infrastructure/Data/BackendContext.cs",
                "region": {
                  "startLine": 44,
                  "startColumn": 13,
                  "endLine": 44,
                  "endColumn": 63
                }
              }
            }
          ],
          "properties": {
            "warningLevel": 1
          }
        },
        {
          "ruleId": "S125",
          "level": "warning",
          "message": "Remove this commented out code.",
          "locations": [
            {
              "resultFile": {
                "uri": "file:///C:/Users/Mauricio/source/repos/martloc/martloc.infrastructure/Data/DbInitializer.cs",
                "region": {
                  "startLine": 88,
                  "startColumn": 13,
                  "endLine": 88,
                  "endColumn": 16
                }
              }
            }
          ],
          "properties": {
            "warningLevel": 1
          }
        },
        {
          "ruleId": "S125",
          "level": "warning",
          "message": "Remove this commented out code.",
          "locations": [
            {
              "resultFile": {
                "uri": "file:///C:/Users/Mauricio/source/repos/martloc/martloc.infrastructure/EntityConfig/ClienteMap.cs",
                "region": {
                  "startLine": 11,
                  "startColumn": 5,
                  "endLine": 11,
                  "endColumn": 8
                }
              }
            }
          ],
          "properties": {
            "warningLevel": 1
          }
        },
        {
          "ruleId": "S3261",
          "level": "warning",
          "message": "Remove this empty namespace.",
          "locations": [
            {
              "resultFile": {
                "uri": "file:///C:/Users/Mauricio/source/repos/martloc/martloc.infrastructure/EntityConfig/ClienteMap.cs",
                "region": {
                  "startLine": 8,
                  "startColumn": 1,
                  "endLine": 21,
                  "endColumn": 2
                }
              }
            }
          ],
          "properties": {
            "warningLevel": 1
          }
        },
        {
          "ruleId": "S125",
          "level": "warning",
          "message": "Remove this commented out code.",
          "locations": [
            {
              "resultFile": {
                "uri": "file:///C:/Users/Mauricio/source/repos/martloc/martloc.infrastructure/EntityConfig/EquipamentoMap.cs",
                "region": {
                  "startLine": 17,
                  "startColumn": 13,
                  "endLine": 17,
                  "endColumn": 82
                }
              }
            }
          ],
          "properties": {
            "warningLevel": 1
          }
        },
        {
          "ruleId": "S1128",
          "level": "warning",
          "message": "Remove this unnecessary 'using'.",
          "locations": [
            {
              "resultFile": {
                "uri": "file:///C:/Users/Mauricio/source/repos/martloc/martloc.infrastructure/Data/DbInitializer.cs",
                "region": {
                  "startLine": 6,
                  "startColumn": 1,
                  "endLine": 6,
                  "endColumn": 34
                }
              }
            }
          ],
          "properties": {
            "warningLevel": 1
          }
        },
        {
          "ruleId": "S1128",
          "level": "warning",
          "message": "Remove this unnecessary 'using'.",
          "locations": [
            {
              "resultFile": {
                "uri": "file:///C:/Users/Mauricio/source/repos/martloc/martloc.infrastructure/Data/DbInitializer.cs",
                "region": {
                  "startLine": 8,
                  "startColumn": 1,
                  "endLine": 8,
                  "endColumn": 19
                }
              }
            }
          ],
          "properties": {
            "warningLevel": 1
          }
        },
        {
          "ruleId": "S1128",
          "level": "warning",
          "message": "Remove this unnecessary 'using'.",
          "locations": [
            {
              "resultFile": {
                "uri": "file:///C:/Users/Mauricio/source/repos/martloc/martloc.infrastructure/EntityConfig/ClienteMap.cs",
                "region": {
                  "startLine": 1,
                  "startColumn": 1,
                  "endLine": 1,
                  "endColumn": 38
                }
              }
            }
          ],
          "properties": {
            "warningLevel": 1
          }
        },
        {
          "ruleId": "S1128",
          "level": "warning",
          "message": "Remove this unnecessary 'using'.",
          "locations": [
            {
              "resultFile": {
                "uri": "file:///C:/Users/Mauricio/source/repos/martloc/martloc.infrastructure/EntityConfig/ClienteMap.cs",
                "region": {
                  "startLine": 2,
                  "startColumn": 1,
                  "endLine": 2,
                  "endColumn": 37
                }
              }
            }
          ],
          "properties": {
            "warningLevel": 1
          }
        },
        {
          "ruleId": "S1128",
          "level": "warning",
          "message": "Remove this unnecessary 'using'.",
          "locations": [
            {
              "resultFile": {
                "uri": "file:///C:/Users/Mauricio/source/repos/martloc/martloc.infrastructure/EntityConfig/ClienteMap.cs",
                "region": {
                  "startLine": 3,
                  "startColumn": 1,
                  "endLine": 3,
                  "endColumn": 55
                }
              }
            }
          ],
          "properties": {
            "warningLevel": 1
          }
        },
        {
          "ruleId": "S1128",
          "level": "warning",
          "message": "Remove this unnecessary 'using'.",
          "locations": [
            {
              "resultFile": {
                "uri": "file:///C:/Users/Mauricio/source/repos/martloc/martloc.infrastructure/EntityConfig/ClienteMap.cs",
                "region": {
                  "startLine": 4,
                  "startColumn": 1,
                  "endLine": 4,
                  "endColumn": 14
                }
              }
            }
          ],
          "properties": {
            "warningLevel": 1
          }
        },
        {
          "ruleId": "S1128",
          "level": "warning",
          "message": "Remove this unnecessary 'using'.",
          "locations": [
            {
              "resultFile": {
                "uri": "file:///C:/Users/Mauricio/source/repos/martloc/martloc.infrastructure/EntityConfig/ClienteMap.cs",
                "region": {
                  "startLine": 5,
                  "startColumn": 1,
                  "endLine": 5,
                  "endColumn": 34
                }
              }
            }
          ],
          "properties": {
            "warningLevel": 1
          }
        },
        {
          "ruleId": "S1128",
          "level": "warning",
          "message": "Remove this unnecessary 'using'.",
          "locations": [
            {
              "resultFile": {
                "uri": "file:///C:/Users/Mauricio/source/repos/martloc/martloc.infrastructure/EntityConfig/ClienteMap.cs",
                "region": {
                  "startLine": 6,
                  "startColumn": 1,
                  "endLine": 6,
                  "endColumn": 19
                }
              }
            }
          ],
          "properties": {
            "warningLevel": 1
          }
        },
        {
          "ruleId": "S1128",
          "level": "warning",
          "message": "Remove this unnecessary 'using'.",
          "locations": [
            {
              "resultFile": {
                "uri": "file:///C:/Users/Mauricio/source/repos/martloc/martloc.infrastructure/EntityConfig/EquipamentoMap.cs",
                "region": {
                  "startLine": 4,
                  "startColumn": 1,
                  "endLine": 4,
                  "endColumn": 14
                }
              }
            }
          ],
          "properties": {
            "warningLevel": 1
          }
        },
        {
          "ruleId": "S1128",
          "level": "warning",
          "message": "Remove this unnecessary 'using'.",
          "locations": [
            {
              "resultFile": {
                "uri": "file:///C:/Users/Mauricio/source/repos/martloc/martloc.infrastructure/EntityConfig/EquipamentoMap.cs",
                "region": {
                  "startLine": 5,
                  "startColumn": 1,
                  "endLine": 5,
                  "endColumn": 34
                }
              }
            }
          ],
          "properties": {
            "warningLevel": 1
          }
        },
        {
          "ruleId": "S1128",
          "level": "warning",
          "message": "Remove this unnecessary 'using'.",
          "locations": [
            {
              "resultFile": {
                "uri": "file:///C:/Users/Mauricio/source/repos/martloc/martloc.infrastructure/EntityConfig/EquipamentoMap.cs",
                "region": {
                  "startLine": 6,
                  "startColumn": 1,
                  "endLine": 6,
                  "endColumn": 19
                }
              }
            }
          ],
          "properties": {
            "warningLevel": 1
          }
        },
        {
          "ruleId": "S1128",
          "level": "warning",
          "message": "Remove this unnecessary 'using'.",
          "locations": [
            {
              "resultFile": {
                "uri": "file:///C:/Users/Mauricio/source/repos/martloc/martloc.infrastructure/EntityConfig/LocacaoItensMap.cs",
                "region": {
                  "startLine": 4,
                  "startColumn": 1,
                  "endLine": 4,
                  "endColumn": 14
                }
              }
            }
          ],
          "properties": {
            "warningLevel": 1
          }
        },
        {
          "ruleId": "S1128",
          "level": "warning",
          "message": "Remove this unnecessary 'using'.",
          "locations": [
            {
              "resultFile": {
                "uri": "file:///C:/Users/Mauricio/source/repos/martloc/martloc.infrastructure/EntityConfig/LocacaoItensMap.cs",
                "region": {
                  "startLine": 5,
                  "startColumn": 1,
                  "endLine": 5,
                  "endColumn": 34
                }
              }
            }
          ],
          "properties": {
            "warningLevel": 1
          }
        },
        {
          "ruleId": "S1128",
          "level": "warning",
          "message": "Remove this unnecessary 'using'.",
          "locations": [
            {
              "resultFile": {
                "uri": "file:///C:/Users/Mauricio/source/repos/martloc/martloc.infrastructure/EntityConfig/LocacaoItensMap.cs",
                "region": {
                  "startLine": 6,
                  "startColumn": 1,
                  "endLine": 6,
                  "endColumn": 19
                }
              }
            }
          ],
          "properties": {
            "warningLevel": 1
          }
        },
        {
          "ruleId": "S1128",
          "level": "warning",
          "message": "Remove this unnecessary 'using'.",
          "locations": [
            {
              "resultFile": {
                "uri": "file:///C:/Users/Mauricio/source/repos/martloc/martloc.infrastructure/EntityConfig/PessoaMap.cs",
                "region": {
                  "startLine": 4,
                  "startColumn": 1,
                  "endLine": 4,
                  "endColumn": 14
                }
              }
            }
          ],
          "properties": {
            "warningLevel": 1
          }
        },
        {
          "ruleId": "S1128",
          "level": "warning",
          "message": "Remove this unnecessary 'using'.",
          "locations": [
            {
              "resultFile": {
                "uri": "file:///C:/Users/Mauricio/source/repos/martloc/martloc.infrastructure/EntityConfig/PessoaMap.cs",
                "region": {
                  "startLine": 5,
                  "startColumn": 1,
                  "endLine": 5,
                  "endColumn": 34
                }
              }
            }
          ],
          "properties": {
            "warningLevel": 1
          }
        },
        {
          "ruleId": "S1128",
          "level": "warning",
          "message": "Remove this unnecessary 'using'.",
          "locations": [
            {
              "resultFile": {
                "uri": "file:///C:/Users/Mauricio/source/repos/martloc/martloc.infrastructure/EntityConfig/PessoaMap.cs",
                "region": {
                  "startLine": 6,
                  "startColumn": 1,
                  "endLine": 6,
                  "endColumn": 19
                }
              }
            }
          ],
          "properties": {
            "warningLevel": 1
          }
        },
        {
          "ruleId": "S1128",
          "level": "warning",
          "message": "Remove this unnecessary 'using'.",
          "locations": [
            {
              "resultFile": {
                "uri": "file:///C:/Users/Mauricio/source/repos/martloc/martloc.infrastructure/Repositoty/ClienteRepository.cs",
                "region": {
                  "startLine": 4,
                  "startColumn": 1,
                  "endLine": 4,
                  "endColumn": 14
                }
              }
            }
          ],
          "properties": {
            "warningLevel": 1
          }
        },
        {
          "ruleId": "S1128",
          "level": "warning",
          "message": "Remove this unnecessary 'using'.",
          "locations": [
            {
              "resultFile": {
                "uri": "file:///C:/Users/Mauricio/source/repos/martloc/martloc.infrastructure/Repositoty/ClienteRepository.cs",
                "region": {
                  "startLine": 5,
                  "startColumn": 1,
                  "endLine": 5,
                  "endColumn": 34
                }
              }
            }
          ],
          "properties": {
            "warningLevel": 1
          }
        },
        {
          "ruleId": "S1128",
          "level": "warning",
          "message": "Remove this unnecessary 'using'.",
          "locations": [
            {
              "resultFile": {
                "uri": "file:///C:/Users/Mauricio/source/repos/martloc/martloc.infrastructure/Repositoty/ClienteRepository.cs",
                "region": {
                  "startLine": 7,
                  "startColumn": 1,
                  "endLine": 7,
                  "endColumn": 19
                }
              }
            }
          ],
          "properties": {
            "warningLevel": 1
          }
        },
        {
          "ruleId": "S1128",
          "level": "warning",
          "message": "Remove this unnecessary 'using'.",
          "locations": [
            {
              "resultFile": {
                "uri": "file:///C:/Users/Mauricio/source/repos/martloc/martloc.infrastructure/Repositoty/FisicaRepository.cs",
                "region": {
                  "startLine": 4,
                  "startColumn": 1,
                  "endLine": 4,
                  "endColumn": 14
                }
              }
            }
          ],
          "properties": {
            "warningLevel": 1
          }
        },
        {
          "ruleId": "S1128",
          "level": "warning",
          "message": "Remove this unnecessary 'using'.",
          "locations": [
            {
              "resultFile": {
                "uri": "file:///C:/Users/Mauricio/source/repos/martloc/martloc.infrastructure/Repositoty/FisicaRepository.cs",
                "region": {
                  "startLine": 5,
                  "startColumn": 1,
                  "endLine": 5,
                  "endColumn": 34
                }
              }
            }
          ],
          "properties": {
            "warningLevel": 1
          }
        },
        {
          "ruleId": "S1128",
          "level": "warning",
          "message": "Remove this unnecessary 'using'.",
          "locations": [
            {
              "resultFile": {
                "uri": "file:///C:/Users/Mauricio/source/repos/martloc/martloc.infrastructure/Repositoty/FisicaRepository.cs",
                "region": {
                  "startLine": 6,
                  "startColumn": 1,
                  "endLine": 6,
                  "endColumn": 19
                }
              }
            }
          ],
          "properties": {
            "warningLevel": 1
          }
        },
        {
          "ruleId": "S1128",
          "level": "warning",
          "message": "Remove this unnecessary 'using'.",
          "locations": [
            {
              "resultFile": {
                "uri": "file:///C:/Users/Mauricio/source/repos/martloc/martloc.infrastructure/Repositoty/LocacaoRepository.cs",
                "region": {
                  "startLine": 5,
                  "startColumn": 1,
                  "endLine": 5,
                  "endColumn": 14
                }
              }
            }
          ],
          "properties": {
            "warningLevel": 1
          }
        },
        {
          "ruleId": "S1128",
          "level": "warning",
          "message": "Remove this unnecessary 'using'.",
          "locations": [
            {
              "resultFile": {
                "uri": "file:///C:/Users/Mauricio/source/repos/martloc/martloc.infrastructure/Repositoty/LocacaoRepository.cs",
                "region": {
                  "startLine": 6,
                  "startColumn": 1,
                  "endLine": 6,
                  "endColumn": 34
                }
              }
            }
          ],
          "properties": {
            "warningLevel": 1
          }
        },
        {
          "ruleId": "S1128",
          "level": "warning",
          "message": "Remove this unnecessary 'using'.",
          "locations": [
            {
              "resultFile": {
                "uri": "file:///C:/Users/Mauricio/source/repos/martloc/martloc.infrastructure/Repositoty/LocacaoRepository.cs",
                "region": {
                  "startLine": 8,
                  "startColumn": 1,
                  "endLine": 8,
                  "endColumn": 19
                }
              }
            }
          ],
          "properties": {
            "warningLevel": 1
          }
        },
        {
          "ruleId": "S1128",
          "level": "warning",
          "message": "Remove this unnecessary 'using'.",
          "locations": [
            {
              "resultFile": {
                "uri": "file:///C:/Users/Mauricio/source/repos/martloc/martloc.infrastructure/Repositoty/MarcaRepository.cs",
                "region": {
                  "startLine": 4,
                  "startColumn": 1,
                  "endLine": 4,
                  "endColumn": 14
                }
              }
            }
          ],
          "properties": {
            "warningLevel": 1
          }
        },
        {
          "ruleId": "S1128",
          "level": "warning",
          "message": "Remove this unnecessary 'using'.",
          "locations": [
            {
              "resultFile": {
                "uri": "file:///C:/Users/Mauricio/source/repos/martloc/martloc.infrastructure/Repositoty/MarcaRepository.cs",
                "region": {
                  "startLine": 5,
                  "startColumn": 1,
                  "endLine": 5,
                  "endColumn": 34
                }
              }
            }
          ],
          "properties": {
            "warningLevel": 1
          }
        },
        {
          "ruleId": "S1128",
          "level": "warning",
          "message": "Remove this unnecessary 'using'.",
          "locations": [
            {
              "resultFile": {
                "uri": "file:///C:/Users/Mauricio/source/repos/martloc/martloc.infrastructure/Repositoty/MarcaRepository.cs",
                "region": {
                  "startLine": 6,
                  "startColumn": 1,
                  "endLine": 6,
                  "endColumn": 19
                }
              }
            }
          ],
          "properties": {
            "warningLevel": 1
          }
        },
        {
          "ruleId": "S1128",
          "level": "warning",
          "message": "Remove this unnecessary 'using'.",
          "locations": [
            {
              "resultFile": {
                "uri": "file:///C:/Users/Mauricio/source/repos/martloc/martloc.infrastructure/Repositoty/PessoaRepository.cs",
                "region": {
                  "startLine": 4,
                  "startColumn": 1,
                  "endLine": 4,
                  "endColumn": 14
                }
              }
            }
          ],
          "properties": {
            "warningLevel": 1
          }
        },
        {
          "ruleId": "S1128",
          "level": "warning",
          "message": "Remove this unnecessary 'using'.",
          "locations": [
            {
              "resultFile": {
                "uri": "file:///C:/Users/Mauricio/source/repos/martloc/martloc.infrastructure/Repositoty/PessoaRepository.cs",
                "region": {
                  "startLine": 5,
                  "startColumn": 1,
                  "endLine": 5,
                  "endColumn": 34
                }
              }
            }
          ],
          "properties": {
            "warningLevel": 1
          }
        },
        {
          "ruleId": "S1128",
          "level": "warning",
          "message": "Remove this unnecessary 'using'.",
          "locations": [
            {
              "resultFile": {
                "uri": "file:///C:/Users/Mauricio/source/repos/martloc/martloc.infrastructure/Repositoty/PessoaRepository.cs",
                "region": {
                  "startLine": 6,
                  "startColumn": 1,
                  "endLine": 6,
                  "endColumn": 19
                }
              }
            }
          ],
          "properties": {
            "warningLevel": 1
          }
        },
        {
          "ruleId": "S1128",
          "level": "warning",
          "message": "Remove this unnecessary 'using'.",
          "locations": [
            {
              "resultFile": {
                "uri": "file:///C:/Users/Mauricio/source/repos/martloc/martloc.infrastructure/Repositoty/Repository.cs",
                "region": {
                  "startLine": 8,
                  "startColumn": 1,
                  "endLine": 8,
                  "endColumn": 19
                }
              }
            }
          ],
          "properties": {
            "warningLevel": 1
          }
        },
        {
          "ruleId": "S927",
          "level": "warning",
          "message": "Rename parameter 'modelBuilder' to 'builder' to match the base class declaration.",
          "locations": [
            {
              "resultFile": {
                "uri": "file:///C:/Users/Mauricio/source/repos/martloc/martloc.infrastructure/Data/BackendContext.cs",
                "region": {
                  "startLine": 32,
                  "startColumn": 62,
                  "endLine": 32,
                  "endColumn": 74
                }
              }
            }
          ],
          "properties": {
            "warningLevel": 1
          }
        }
      ],
      "rules": {
        "S1128": {
          "id": "S1128",
          "shortDescription": "Unused \"using\" should be removed",
          "fullDescription": "Although unnecessary using won't change anything to the produced application, removing them:",
          "defaultLevel": "warning",
          "helpUri": "https://rules.sonarsource.com/csharp/RSPEC-1128",
          "properties": {
            "category": "Minor Code Smell",
            "isEnabledByDefault": true,
            "tags": [
              "C#",
              "SonarWay",
              "MainSourceScope",
              "TestSourceScope"
            ]
          }
        },
        "S125": {
          "id": "S125",
          "shortDescription": "Sections of code should not be commented out",
          "fullDescription": "Programmers should not comment out code as it bloats programs and reduces readability.",
          "defaultLevel": "warning",
          "helpUri": "https://rules.sonarsource.com/csharp/RSPEC-125",
          "properties": {
            "category": "Major Code Smell",
            "isEnabledByDefault": true,
            "tags": [
              "C#",
              "SonarWay",
              "MainSourceScope",
              "TestSourceScope"
            ]
          }
        },
        "S3261": {
          "id": "S3261",
          "shortDescription": "Namespaces should not be empty",
          "fullDescription": "Namespaces with no lines of code clutter a project and should be removed. ",
          "defaultLevel": "warning",
          "helpUri": "https://rules.sonarsource.com/csharp/RSPEC-3261",
          "properties": {
            "category": "Minor Code Smell",
            "isEnabledByDefault": true,
            "tags": [
              "C#",
              "SonarWay",
              "MainSourceScope",
              "TestSourceScope"
            ]
          }
        },
        "S927": {
          "id": "S927",
          "shortDescription": "parameter names should match base declaration and other partial definitions",
          "fullDescription": "The name of a parameter in an externally visible method override does not match the name of the parameter in the base declaration of the method, or the name of the parameter in the interface declaration of the method or the name of any other partial definition.",
          "defaultLevel": "warning",
          "helpUri": "https://rules.sonarsource.com/csharp/RSPEC-927",
          "properties": {
            "category": "Critical Code Smell",
            "isEnabledByDefault": true,
            "tags": [
              "C#",
              "SonarWay",
              "MainSourceScope",
              "TestSourceScope"
            ]
          }
        }
      }
    }
  ]
}